cstest2/main.py
cstest2/modul.py
cstest2-0.0.0.1.dist-info/METADATA
cstest2-0.0.0.1.dist-info/WHEEL
cstest2-0.0.0.1.dist-info/top_level.txt
cstest2-0.0.0.1.dist-info/RECORD
