Metadata-Version: 2.1
Name: cstest2
Version: 0.0.0.1
Summary: BMI 측정
Home-page: https://blog.naver.com/fpqaut
Author: Demeno
Author-email: fpqaut@naver.com
License: MIT
Platform: UNKNOWN
Requires-Python: >=3
